flask_gfm.py
Flask_GFM-0.1.1.dist-info/LICENSE
Flask_GFM-0.1.1.dist-info/METADATA
Flask_GFM-0.1.1.dist-info/WHEEL
Flask_GFM-0.1.1.dist-info/top_level.txt
Flask_GFM-0.1.1.dist-info/RECORD
